{
  "dateAdded": "2018-01-27T05:06:52Z",
  "city": "Boston",
  "hotel_name": "W Boston",
  "hotel_state": "MA",
  "review_text": "Bad: The parking rates are outrageous (59 USD/day for valet), but this is for all of Boston, not just this hotel. . Good: Great location, very convenient for Boston Commons, subway and good restos. Hotel was very nicely appointed with great products. Wish we had time to use Bliss Spa!",
  "review_title": "Wonderful stay",
  "id": "c8bbfb37-2508-4a84-b362-8f8eeb788f62"
}