{
  "dateAdded": "2018-04-09T05:56:34Z",
  "city": "Las Vegas",
  "hotel_name": "Main Street Station Casino Brewery Hotel",
  "hotel_state": "NV",
  "review_text": "Bad: The elevator to the parkade requires some maintenance - at least a wet mop to kill whatever is lurking on the floor!. Good: This resort hotel is amazing - the location in perfect, the rooms are huge, and absolutely spotless!",
  "review_title": "Excellence - and without a resort fee!",
  "id": "5fe44188-d0cf-4019-8c3b-66f6a2d8bce3"
}