{
  "dateAdded": "2015-11-28T19:19:35Z",
  "city": "Hanover",
  "hotel_name": "Aloft Arundel Mills",
  "hotel_state": "MD",
  "review_text": "Beautiful rooms and the nicest people working there. The front desk lady, Olivia, was extremely patient and helpful. We had lots of questions and she had just as many answers. The rooms were sleek and modern. The only thing that would make this hotel better would be free breakfast, but I really am asking for a lot. A++ stay. Thank... More",
  "review_title": "Worth the money",
  "id": "79384e39-b0a5-4fd7-a70f-462421942f02"
}