{
  "dateAdded": "2015-10-21T17:43:40Z",
  "city": "San Diego",
  "hotel_name": "Fairmont Grand Del Mar",
  "hotel_state": "CA",
  "review_text": "This resort is GORGEOUS!! Check in was perfect our room wasnt ready (we were there early) so they took my phone number while we had drinks by the pool and in 20 mins or so our room was ready! The next day we had spa appts and the receptionist heard it was our honeymoon trip so after our massages we... More",
  "review_title": "Amazing Experience",
  "id": "304fb0cc-8f2e-4cec-95a7-56c9118fdbca"
}